atek/__init__.py
atek/connect.py
atek/connect2.py
atek/conversion.py
atek/display.py
atek/tools.py
atek/xlsx.py
atek-0.1.42.dist-info/WHEEL
atek-0.1.42.dist-info/METADATA
atek-0.1.42.dist-info/RECORD
