Metadata-Version: 2.1
Name: atek
Version: 0.1.42
Summary: 
Author: JediHero
Author-email: hansen.rusty@gmail.com
Requires-Python: >=3.8,<4.0
Classifier: Programming Language :: Python :: 3
Classifier: Programming Language :: Python :: 3.8
Requires-Dist: censusdata (>=1.8,<2.0)
Requires-Dist: cytoolz (>=0.10.1,<0.11.0)
Requires-Dist: jupyter (>=1.0.0,<2.0.0)
Requires-Dist: openpyxl (>=3.0.5,<4.0.0)
Requires-Dist: pandas (>=1.1.0,<2.0.0)
Requires-Dist: pydantic[dotenv] (>=1.7.2,<2.0.0)
Requires-Dist: pydomo (>=0.2.3,<0.3.0)
Requires-Dist: pymysql (>=0.10.0,<0.11.0)
Requires-Dist: requests (>=2.24.0,<3.0.0)
Requires-Dist: sshtunnel (>=0.1.5,<0.2.0)
Requires-Dist: tabulate (>=0.8.7,<0.9.0)
Requires-Dist: toolz (>=0.11.1,<0.12.0)
Requires-Dist: us (>=2.0.2,<3.0.0)
Requires-Dist: xlrd (>=1.2.0,<2.0.0)
Requires-Dist: xlsxwriter (>=1.3.6,<2.0.0)
